tensorsignatures/__init__.py
tensorsignatures/bootstrap.py
tensorsignatures/cli.py
tensorsignatures/config.py
tensorsignatures/data.py
tensorsignatures/plot.py
tensorsignatures/tensorsignatures.py
tensorsignatures/util.py
tensorsignatures/writer.py
tensorsignatures/data/norm.h5
tensorsignatures/data/other.txt
tensorsignatures/data/pcawg.pkl
tensorsignatures/data/sim_sig.txt
tensorsignatures-0.5.0.dist-info/AUTHORS.rst
tensorsignatures-0.5.0.dist-info/LICENSE
tensorsignatures-0.5.0.dist-info/METADATA
tensorsignatures-0.5.0.dist-info/WHEEL
tensorsignatures-0.5.0.dist-info/entry_points.txt
tensorsignatures-0.5.0.dist-info/top_level.txt
tensorsignatures-0.5.0.dist-info/RECORD
