Metadata-Version: 2.1
Name: tensorsignatures
Version: 0.5.0
Summary: Tensorframework for mutational signature analysis.
Home-page: https://github.com/sagar87/tensorsignatures
Author: Harald Sager Vohringer
Author-email: harald.voeh@gmail.com
License: MIT license
Keywords: tensorsignatures
Platform: UNKNOWN
Classifier: Development Status :: 2 - Pre-Alpha
Classifier: Intended Audience :: Developers
Classifier: License :: OSI Approved :: MIT License
Classifier: Natural Language :: English
Classifier: Programming Language :: Python :: 3.6
Requires-Dist: Click (==7.0)
Requires-Dist: scipy (==1.3.2)
Requires-Dist: pandas (==0.25.3)
Requires-Dist: h5py (==2.10.0)
Requires-Dist: numpy (<1.17,>=1.14.5)
Requires-Dist: scikit-learn (==0.21.3)
Requires-Dist: matplotlib (<3.2.0,>=3.0.0)
Requires-Dist: tensorflow (<=1.15.0)
Requires-Dist: tqdm (==4.39.0)
